sphinx_substitution_extensions/__init__.py
sphinx_substitution_extensions/py.typed
sphinx_substitution_extensions/shared.py
sphinx_substitution_extensions/spelling_private_dict.txt
sphinx_substitution_extensions-2025.12.15.dist-info/licenses/LICENSE
sphinx_substitution_extensions-2025.12.15.dist-info/METADATA
sphinx_substitution_extensions-2025.12.15.dist-info/WHEEL
sphinx_substitution_extensions-2025.12.15.dist-info/top_level.txt
sphinx_substitution_extensions-2025.12.15.dist-info/RECORD
